logbesselk/__init__.py
logbesselk/jax/__init__.py
logbesselk/jax/asymptotic.py
logbesselk/jax/cfraction.py
logbesselk/jax/ica.py
logbesselk/jax/integral.py
logbesselk/jax/math.py
logbesselk/jax/misc.py
logbesselk/jax/sca.py
logbesselk/jax/series.py
logbesselk/jax/utils.py
logbesselk/jax/wrap.py
logbesselk/tensorflow/__init__.py
logbesselk/tensorflow/asymptotic.py
logbesselk/tensorflow/cfraction.py
logbesselk/tensorflow/ica.py
logbesselk/tensorflow/integral.py
logbesselk/tensorflow/math.py
logbesselk/tensorflow/misc.py
logbesselk/tensorflow/sca.py
logbesselk/tensorflow/series.py
logbesselk/tensorflow/utils.py
logbesselk/tensorflow/wrap.py
logbesselk-3.4.0.dist-info/METADATA
logbesselk-3.4.0.dist-info/WHEEL
logbesselk-3.4.0.dist-info/licenses/LICENSE.txt
logbesselk-3.4.0.dist-info/RECORD
