Metadata-Version: 2.3
Name: logbesselk
Version: 3.4.0
Summary: Provide function to calculate the modified Bessel function of the second kind
Author-email: TAKEKAWA Takashi <takekawa@tk2lab.org>
License-Expression: Apache-2.0
License-File: LICENSE.txt
Classifier: Programming Language :: Python :: 3.10
Classifier: Programming Language :: Python :: 3.11
Classifier: Programming Language :: Python :: 3.12
Requires-Python: >=3.10
Provides-Extra: jax
Requires-Dist: jax; extra == 'jax'
Requires-Dist: jaxlib; extra == 'jax'
Provides-Extra: jaxcuda
Requires-Dist: jax[cuda12]; extra == 'jaxcuda'
Requires-Dist: jaxlib; extra == 'jaxcuda'
Provides-Extra: tensorflow
Requires-Dist: tensorflow>=2.8; extra == 'tensorflow'
